{
  "version": 1,
  "shard": "f7",
  "words": {
    "W00098": {
      "id": "W00098",
      "surface": "祖母",
      "kana": "そぼ",
      "reading": "sobo",
      "pos": "noun",
      "meanings": [
        "grandmother (one's own)"
      ],
      "first_story": "story_31",
      "occurrences": 12,
      "last_seen_story": "story_55"
    },
    "W00212": {
      "id": "W00212",
      "surface": "緑",
      "kana": "みどり",
      "reading": "midori",
      "pos": "noun",
      "meanings": [
        "green",
        "verdure"
      ],
      "first_story": "story_46",
      "occurrences": 4,
      "last_seen_story": "story_56"
    }
  }
}
