{
  "story_id": 29,
  "title": {
    "jp": "ベンチの友達",
    "en": "A Friend on the Bench"
  },
  "sentences": [
    {
      "jp": "春の朝、公園を歩きます。",
      "en": "On a spring morning, I walk in the park."
    },
    {
      "jp": "ベンチに、古い友達が座ります。",
      "en": "An old friend sits on a bench."
    },
    {
      "jp": "私も、ベンチに座ります。",
      "en": "I also sit on the bench."
    },
    {
      "jp": "二人で、店のお茶を飲みます。",
      "en": "The two drink tea from the shop."
    },
    {
      "jp": "友達の家族の写真を見ます。",
      "en": "We look at a photo of my friend's family."
    },
    {
      "jp": "写真に、友達の母がいます。",
      "en": "In the photo, my friend's mother is there."
    },
    {
      "jp": "友達の母は、美しいです。",
      "en": "My friend's mother is beautiful."
    },
    {
      "jp": "友達の家族は、元気だと思います。",
      "en": "I think my friend's family is well."
    },
    {
      "jp": "私も、嬉しいです。",
      "en": "I am happy too."
    },
    {
      "jp": "友達は、ベンチから立ちます。",
      "en": "My friend stands up from the bench."
    },
    {
      "jp": "私も、立ちます。",
      "en": "I stand up too."
    },
    {
      "jp": "ベンチの上に、雪があります。",
      "en": "On the bench, there is snow."
    },
    {
      "jp": "町の角は明るいです。",
      "en": "The town's corner is bright."
    },
    {
      "jp": "雨ですが、公園は静かです。",
      "en": "It is raining, but the park is quiet."
    },
    {
      "jp": "でも、友達は来ます。",
      "en": "But my friend comes."
    },
    {
      "jp": "「元気です」と友達は言います。",
      "en": "'I am well,' my friend says."
    }
  ]
}
