{
  "story_id": 38,
  "title": {
    "jp": "本の店の人",
    "en": "The Person at the Bookstore"
  },
  "sentences": [
    {
      "jp": "本の店にいます。",
      "en": "I am at the bookstore."
    },
    {
      "jp": "店は小さくて静かです。",
      "en": "The shop is small and quiet."
    },
    {
      "jp": "私は店が好きです。",
      "en": "I like the shop."
    },
    {
      "jp": "そばに人がいます。",
      "en": "Beside me, there is a person."
    },
    {
      "jp": "人は本を読みます。",
      "en": "The person is reading a book."
    },
    {
      "jp": "静かな人です。",
      "en": "A quiet person."
    },
    {
      "jp": "私も本を読みます。",
      "en": "I read a book too."
    },
    {
      "jp": "人は「いい本ですね」と言います。",
      "en": "The person says, \"It is a good book, isn't it.\""
    },
    {
      "jp": "優しい人です。",
      "en": "A kind person."
    },
    {
      "jp": "私は人を思います。",
      "en": "I think of the person."
    },
    {
      "jp": "店で本を読みたいです。",
      "en": "I want to read books at the shop."
    },
    {
      "jp": "私は人を見たいです。",
      "en": "I want to see the person."
    },
    {
      "jp": "風と一緒に、私は待ちます。",
      "en": "Together with the wind, I wait."
    },
    {
      "jp": "「これはいい本です」と本の店の人は言います。",
      "en": "\"This is a good book,\" the shop person says."
    },
    {
      "jp": "池のそばに、本の店があります。",
      "en": "Beside the pond, there is a bookshop."
    },
    {
      "jp": "店の人は「明日も来ます」と言います。",
      "en": "The shop person says, \"I will come tomorrow too.\""
    },
    {
      "jp": "白い雲を見ます。",
      "en": "I look at the white clouds."
    }
  ]
}
