{
  "story_id": 12,
  "title": {
    "jp": "雨の朝",
    "en": "A Rainy Morning"
  },
  "sentences": [
    {
      "jp": "今朝、早い雨が来ます。",
      "en": "This morning, an early rain comes."
    },
    {
      "jp": "猫は椅子にいます。",
      "en": "The cat is on the chair."
    },
    {
      "jp": "猫は白い窓を見ます。",
      "en": "The cat looks at the white window."
    },
    {
      "jp": "「猫は雨を見ます」と私は思います。",
      "en": "\"The cat is watching the rain,\" I think."
    },
    {
      "jp": "そして、猫は私を見ます。",
      "en": "And then, the cat looks at me."
    },
    {
      "jp": "猫は私のお茶を見ます。",
      "en": "The cat watches my tea."
    },
    {
      "jp": "私はお茶を飲んで、待ちます。",
      "en": "I drink tea and wait."
    },
    {
      "jp": "重い雨と猫と朝です。",
      "en": "Heavy rain, and cat, and morning."
    }
  ]
}
